{
  "candidate_error_counts": {
    "background_or_non_instance": 3,
    "mixed_multiple_instances": 1,
    "weak_or_wrong_geometry": 7
  },
  "geometry_oracle": {
    "candidate_precision_at_iou25": 0.09090909090909091,
    "candidate_precision_at_iou50": 0.0,
    "gt_recall_at_iou25": 0.058823529411764705,
    "gt_recall_at_iou50": 0.0,
    "mean_best_candidate_iou": 0.0453931211658321
  },
  "gt_status_counts": {
    "covered": 1,
    "missed": 16
  },
  "num_candidates": 11,
  "num_gt_instances": 17,
  "scene_name": "scene0019_01"
}
